<?xml version="1.0"?>
<HAPSIM>
   <General>
      <Build>2005</Build>
      <Position>
         <top>317</top>
         <bottom>617</bottom>
         <left>960</left>
         <right>1360</right>
      </Position>
      <StayOnTop>1</StayOnTop>
      <Target>ATMega128</Target>
   </General>
   <Views>
      <LCD>
         <Name>LCD1</Name>
         <Position>
            <top>25</top>
            <left>68</left>
         </Position>
         <DisplayConfig>
            <columns>16</columns>
            <rows>2</rows>
            <bkColor>0xe6ef8f</bkColor>
            <size>2</size>
         </DisplayConfig>
         <PortMapping>
            <DataPort>
               <Port>PORTA</Port>
               <HighNibble>bit 4..7</HighNibble>
               <LowNibble>N.C.</LowNibble>
            </DataPort>
            <EnablePin>
               <Port>PORTA</Port>
               <Bit>1</Bit>
            </EnablePin>
            <RW_Pin>
               <WriteOnly>1</WriteOnly>
               <Port>PORTG</Port>
               <Bit>0</Bit>
            </RW_Pin>
            <RS_Pin>
               <Port>PORTA</Port>
               <Bit>0</Bit>
            </RS_Pin>
         </PortMapping>
      </LCD>
   </Views>
</HAPSIM>
